clipsync/__init__.py
clipsync/api.py
clipsync/auth.py
clipsync/cli.py
clipsync/monitor.py
clipsync_xdt-0.1.0.dist-info/METADATA
clipsync_xdt-0.1.0.dist-info/WHEEL
clipsync_xdt-0.1.0.dist-info/entry_points.txt
clipsync_xdt-0.1.0.dist-info/top_level.txt
clipsync_xdt-0.1.0.dist-info/RECORD
