Metadata-Version: 2.4
Name: clipsync-xdt
Version: 0.1.0
Summary: A professional cross-platform clipboard synchronization CLI by XDT Labs.
Requires-Python: >=3.8
Requires-Dist: pyperclip
Requires-Dist: firebase-admin
Requires-Dist: click
Requires-Dist: requests
Requires-Dist: rich
Requires-Dist: flask
Requires-Dist: pyfiglet
